aiopt/__init__.py
aiopt/proxy.py
aiopt-0.1.5.dist-info/LICENSE
aiopt-0.1.5.dist-info/METADATA
aiopt-0.1.5.dist-info/WHEEL
aiopt-0.1.5.dist-info/RECORD
